LICENSE.txt
MANIFEST.in
README.md
setup.py
djangocms_slideshow.egg-info/PKG-INFO
djangocms_slideshow.egg-info/SOURCES.txt
djangocms_slideshow.egg-info/dependency_links.txt
djangocms_slideshow.egg-info/not-zip-safe
djangocms_slideshow.egg-info/requires.txt
djangocms_slideshow.egg-info/top_level.txt
slideshow/__init__.py
slideshow/admin.py
slideshow/cms_plugins.py
slideshow/models.py
slideshow/tests.py
slideshow/widgets.py
slideshow/locale/en/LC_MESSAGES/django.mo
slideshow/locale/en/LC_MESSAGES/django.po
slideshow/locale/nl/LC_MESSAGES/django.mo
slideshow/locale/nl/LC_MESSAGES/django.po
slideshow/migrations/0001_initial.py
slideshow/migrations/0002_auto__add_field_image_url__chg_field_image_name.py
slideshow/migrations/__init__.py
slideshow/templates/slideshow/slideshow.html