Metadata-Version: 1.1
Name: djangocms-slideshow
Version: 0.1.5
Summary: A simple django cms slideshow plugin
Home-page: https://github.com/urga/djangocms-slideshow
Author: Urga
Author-email: dries@urga.be
License: GNU
Keywords: slideshow,django,cms,plugin
Platform: UNKNOWN
Classifier: Development Status :: 5 - Production/Stable
Classifier: Natural Language :: Dutch
Classifier: Natural Language :: English
Classifier: Programming Language :: Python :: 2.7
Classifier: Framework :: Django
Classifier: Intended Audience :: Developers
Classifier: Topic :: Internet :: WWW/HTTP :: Dynamic Content
Classifier: Topic :: Multimedia :: Graphics :: Viewers
Classifier: License :: OSI Approved :: GNU General Public License v2 (GPLv2)
Classifier: Operating System :: OS Independent
